perpetuo-0.7.2.dist-info/WHEEL
perpetuo-0.7.2.dist-info/METADATA
perpetuo-0.7.2.dist-info/top_level.txt
perpetuo-0.7.2.dist-info/RECORD
perpetuo-0.7.2.dist-info/licenses/LICENSE
perpetuo-0.7.2.dist-info/licenses/LICENSE.MIT
perpetuo-0.7.2.dist-info/licenses/LICENSE.APACHE2
perpetuo/py.typed
perpetuo/_setup.py
perpetuo/__init__.py
perpetuo/_perpetuo.abi3.so
perpetuo/_perpetuo.pyi
perpetuo/_tests/__init__.py
perpetuo/_tests/test_perpetuo.py
perpetuo-0.7.2.data/scripts/perpetuo
