Metadata-Version: 2.4
Name: perpetuo
Version: 0.7.2
Summary: A stall tracker for Python's GIL and Trio tasks
Author-email: "Nathaniel J. Smith" <njs@pobox.com>
License: MIT OR Apache-2.0
Project-URL: repository, https://github.com/njsmith/perpetuo
Classifier: Programming Language :: Rust
Classifier: Programming Language :: Python :: Implementation :: CPython
Classifier: Intended Audience :: Developers
Classifier: License :: OSI Approved :: MIT License
Classifier: License :: OSI Approved :: Apache Software License
Classifier: Operating System :: POSIX :: Linux
Classifier: Operating System :: MacOS :: MacOS X
Classifier: Operating System :: Microsoft :: Windows
Classifier: Programming Language :: Python :: 3 :: Only
Requires-Python: >=3.9
License-File: LICENSE
License-File: LICENSE.APACHE2
License-File: LICENSE.MIT
Dynamic: license-file
